JacksTools
LumDist
