Metadata-Version: 1.0
Name: JacksTools
Version: 0.1.3
Summary: Collection of Tools that I commonly use
Home-page: http://github.com/Rodot-/
Author: John (Jack) T O'Brien
Author-email: john.t.obrien@drexel.edu
License: GNU
Platform: UNKNOWN
